Tweetoscope_2020_06-1.0.dist-info/DESCRIPTION.rst
Tweetoscope_2020_06-1.0.dist-info/METADATA
Tweetoscope_2020_06-1.0.dist-info/RECORD
Tweetoscope_2020_06-1.0.dist-info/WHEEL
Tweetoscope_2020_06-1.0.dist-info/entry_points.txt
Tweetoscope_2020_06-1.0.dist-info/metadata.json
Tweetoscope_2020_06-1.0.dist-info/top_level.txt
Tweetoscope_2020_06-1.0.dist-info/build/learner/base_library.zip
ml/__init__.py
ml/dashboard.py
ml/hawkes.py
ml/learner.py
ml/predictor.py
ml/utils/__init__.py
ml/utils/config.py
ml/utils/logger.py
