Metadata-Version: 2.0
Name: Tweetoscope-2020-06
Version: 1.0
Summary: Tweetoscope
Home-page: https://gitlab-student.centralesupelec.fr/tweetoscope-mullticolore/tweetou
Author: Anass Elidrissi
Author-email: anasselidrissi97@gmail.com
License: UNKNOWN
Platform: UNKNOWN
Requires-Dist: kafka-python
Requires-Dist: termcolor
